{"pageProps":{"products":[{"_createdAt":"2023-01-23T02:13:54Z","_id":"07a79129-ef6e-43fa-a74f-d25430ab5b0b","_rev":"j4YVoHImg8Ee4Rc7dc7F5k","_type":"product","_updatedAt":"2023-01-28T11:21:41Z","details":"Cap","image":[{"_key":"0ea6d59b624a","_type":"image","asset":{"_ref":"image-29a78fb1f54fc97fbb8d365346b2c509fa0fa2be-850x850-jpg","_type":"reference"}},{"_key":"7b1779f0940f","_type":"image","asset":{"_ref":"image-d30dfd4e1a5cc4329dfdc1afde635caab18407e6-828x824-jpg","_type":"reference"}}],"name":"PINK OPIUM","price":70,"size":"ONE SIZE","slug":{"_type":"slug","current":"LosAngeles"}},{"_createdAt":"2023-01-21T02:37:29Z","_id":"0a8df7a0-1a6d-4e46-b925-ecdc0e577fb9","_rev":"j4YVoHImg8Ee4Rc7dc7U7U","_type":"product","_updatedAt":"2023-01-28T11:24:50Z","disableBtn":false,"image":[{"_key":"e8e134ca7240","_type":"image","asset":{"_ref":"image-9a380ca3f69233d074049fea4e995875f214970c-828x823-jpg","_type":"reference"}},{"_key":"1c9b2128fbf8","_type":"image","asset":{"_ref":"image-4457b92f9e11116c00b04755189de8def6e10574-828x820-jpg","_type":"reference"}}],"name":"PEACH CAP","price":70,"size":"ONE SIZE","slug":{"_type":"slug","current":"PEACH CAP"}},{"_createdAt":"2022-12-21T17:17:21Z","_id":"12d9ce0d-c2de-4da3-b96f-43fb0fa44b72","_rev":"j4YVoHImg8Ee4Rc7eOZwPX","_type":"product","_updatedAt":"2023-02-04T14:10:18Z","details":"cap * cap","disableBtn":false,"image":[{"_key":"53fcc557963f","_type":"image","asset":{"_ref":"image-40f1034cf5168f7002154cf775613af606f13eb3-828x825-jpg","_type":"reference"}},{"_key":"df81a469cd55","_type":"image","asset":{"_ref":"image-cad30d7a5b33c62aa550c4f60aeee075ffd19163-828x817-jpg","_type":"reference"}}],"name":"LEMON OPIUM","price":123,"slug":{"_type":"slug","current":"Cap"}},{"_createdAt":"2023-01-23T02:18:33Z","_id":"14da9271-be73-4687-800d-ec382a390ca4","_rev":"L3N10uNDdNjShnsJuHXx0N","_type":"product","_updatedAt":"2023-01-28T11:23:49Z","details":"Where is Quality ?","image":[{"_key":"13efbe89db24","_type":"image","asset":{"_ref":"image-01c538ee9c0b213536c96391f513272fade479c3-773x773-jpg","_type":"reference"}},{"_key":"c60085c0f2af","_type":"image","asset":{"_ref":"image-5dacf266fa743141d3b41fc1f50afd13d94fb451-865x865-jpg","_type":"reference"}}],"name":"RISK HOODIE","price":210,"size":"S  M  L  XL","slug":{"_type":"slug","current":"Fisk"}},{"_createdAt":"2023-02-04T14:41:41Z","_id":"53bd13e4-9e72-4934-abe3-c78806fc0836","_rev":"L3N10uNDdNjShnsJulgD5B","_type":"product","_updatedAt":"2023-02-04T14:41:41Z","details":"Big Risk embroidery T-shirt ","image":[{"_key":"129768cbb55b","_type":"image","asset":{"_ref":"image-9d96f12b3e345e877266672208642c427e84145f-1280x1178-jpg","_type":"reference"}},{"_key":"7bb9e93514b5","_type":"image","asset":{"_ref":"image-79b98f1c4fa48045c9f4095ba7e64d81d3033203-1642x1434-png","_type":"reference"}}],"name":"Big Risk tee","price":134,"slug":{"_type":"slug","current":"bigRisktee"}},{"_createdAt":"2023-02-04T14:40:21Z","_id":"721dd8f1-22cc-4280-a1d9-a9a38618188b","_rev":"j4YVoHImg8Ee4Rc7eOe16S","_type":"product","_updatedAt":"2023-02-04T14:42:25Z","details":"Neon silk print of neon girl","image":[{"_key":"1f2f8ab7ac22","_type":"image","asset":{"_ref":"image-48e2b753200c6a1ea139d7b99dfbe53c07283f9e-1338x1257-jpg","_type":"reference"}},{"_key":"99676470ca8c","_type":"image","asset":{"_ref":"image-c3928d658c46b7bf03e2a5aea1c7239a9535adec-1278x1184-png","_type":"reference"}}],"name":"neonGirl","price":134,"slug":{"_type":"slug","current":"neonGirl"}},{"_createdAt":"2023-01-23T01:01:16Z","_id":"7317ac25-6c52-4d03-8da6-b780f48b20b7","_rev":"j4YVoHImg8Ee4Rc7dc7Mje","_type":"product","_updatedAt":"2023-01-28T11:23:35Z","details":"Goth","disableBtn":true,"image":[{"_key":"d8f35258e413","_type":"image","asset":{"_ref":"image-aeb52a0d357e30b52875944dc902e33b7786e276-828x819-jpg","_type":"reference"}},{"_key":"7c7d8a1c3692","_type":"image","asset":{"_ref":"image-9dde6b1bb94891a50b2b5ecb9d666557d735eedb-828x822-jpg","_type":"reference"}}],"name":"GOTHIC OPIUM","price":70,"size":"ONE SIZE","slug":{"_type":"slug","current":"Goth"}},{"_createdAt":"2023-01-05T01:22:37Z","_id":"88d40d82-64c2-4593-8949-ac0dc8e2052f","_rev":"L3N10uNDdNjShnsJufa0rN","_type":"product","_updatedAt":"2023-02-03T11:14:48Z","image":[{"_key":"670785f8a8d1","_type":"image","asset":{"_ref":"image-0e56fb819155b5d9e7b69c1b7064d75449f2617b-1338x1257-jpg","_type":"reference"}}],"name":"OPIUM T SHIRT","price":200,"size":"S  M  L  XL","slug":{"_type":"slug","current":"TeeOpium"}},{"_createdAt":"2023-01-23T09:09:55Z","_id":"dbd6fc81-0dfb-4675-b9fa-0df3c55fbd43","_rev":"j4YVoHImg8Ee4Rc7dc7Vvw","_type":"product","_updatedAt":"2023-01-28T11:25:15Z","details":"Skeletons","disableBtn":true,"image":[{"_key":"d914ac29b610","_type":"image","asset":{"_ref":"image-ba61ba42299c3c5073c64457907b229cd5646b6c-748x748-webp","_type":"reference"}}],"name":"FLIP FLOPS","price":120,"size":"41 42 43 ","slug":{"_type":"slug","current":"FlipFlop"}}],"product":{"_createdAt":"2023-01-05T01:22:37Z","_id":"88d40d82-64c2-4593-8949-ac0dc8e2052f","_rev":"L3N10uNDdNjShnsJufa0rN","_type":"product","_updatedAt":"2023-02-03T11:14:48Z","image":[{"_key":"670785f8a8d1","_type":"image","asset":{"_ref":"image-0e56fb819155b5d9e7b69c1b7064d75449f2617b-1338x1257-jpg","_type":"reference"}}],"name":"OPIUM T SHIRT","price":200,"size":"S  M  L  XL","slug":{"_type":"slug","current":"TeeOpium"}}},"__N_SSG":true}